aqiretrieve/__init__.py
aqiretrieve-0.0.3.dist-info/LICENSE
aqiretrieve-0.0.3.dist-info/METADATA
aqiretrieve-0.0.3.dist-info/WHEEL
aqiretrieve-0.0.3.dist-info/top_level.txt
aqiretrieve-0.0.3.dist-info/RECORD
