Metadata-Version: 2.1
Name: aqiretrieve
Version: 0.0.3
Summary: A python package for retrieving AQI from EPA
Home-page: https://github.com/Manojython/aqiretrieve
Author: Sai Manoj
Author-email: mnjkshrm@gmail.com
License: UNKNOWN
Platform: UNKNOWN
Classifier: Programming Language :: Python :: 3
Classifier: License :: OSI Approved :: MIT License
Classifier: Operating System :: OS Independent
Requires-Python: >=3.5
